.DS_Store
nodeweightedbudget/__init__.py
nodeweightedbudget/core.py
nodeweightedbudget-0.0.2.dist-info/METADATA
nodeweightedbudget-0.0.2.dist-info/WHEEL
nodeweightedbudget-0.0.2.dist-info/top_level.txt
nodeweightedbudget-0.0.2.dist-info/RECORD
